{"routes":[{"route":[{"start":{"name":"Stesen LRT Asia Jaya, Jalan 223","id":2776,"code":"1001784","location":[3.104548,101.63843]},"route":{"id":81,"code":"T629","type":3,"name":"Stesen LRT Asia Jaya"},"end":{"name":"Eastin Hotel, Jalan Damansara","id":2608,"code":"1000603","location":[3.128304,101.64286]},"stops":[{"name":"Stesen LRT Asia Jaya, Jalan 223","id":2776,"code":"1001784","location":[3.104548,101.63843],"is_wp":0,"line":""},{"name":"Kodak, Jalan Kemajuan","id":2796,"code":"1001578","location":[3.110434,101.638836],"is_wp":0,"line":""},{"name":"Century Battery, Jalan Kemajuan","id":2797,"code":"1000471","location":[3.11344,101.641506],"is_wp":0,"line":""},{"name":"F&N, Jalan Kemajuan","id":2798,"code":"1000650","location":[3.116482,101.643008],"is_wp":0,"line":""},{"name":"Castell, Jalan Dato' Abu Bakar","id":2799,"code":"1000467","location":[3.119611,101.643204],"is_wp":0,"line":""},{"name":"Eastin Hotel, Jalan Damansara","id":2608,"code":"1000603","location":[3.128304,101.64286],"is_wp":0,"line":""}],"trip":{"id":240,"headsign":"Eastin Hotel"}}],"stops":[{"stop":{"name":"Stesen LRT Asia Jaya, Jalan 223","id":2776,"code":"1001784","location":[3.104548,101.63843]},"trip":{"id":240,"headsign":"Eastin Hotel"},"route":{"id":81,"code":"T629","type":3,"name":"Stesen LRT Asia Jaya"}},{"stop":{"name":"Eastin Hotel, Jalan Damansara","id":2608,"code":"1000603","location":[3.128304,101.64286]},"trip":{"id":240,"headsign":"Eastin Hotel"},"route":{"id":81,"code":"T629","type":3,"name":"Stesen LRT Asia Jaya"}}]},{"route":[{"start":{"name":"Eastin Hotel, Jalan Damansara","id":2608,"code":"1000603","location":[3.128304,101.64286]},"route":{"id":81,"code":"T629","type":3,"name":"Stesen LRT Asia Jaya"},"end":{"name":"Stesen LRT Asia Jaya, Jalan 223","id":2776,"code":"1001784","location":[3.104548,101.63843]},"stops":[{"name":"Eastin Hotel, Jalan Damansara","id":2608,"code":"1000603","location":[3.128304,101.64286],"is_wp":0,"line":""},{"name":"Pangsapuri Tiara 1, Jalan 17\/1","id":2800,"code":"1002184","location":[3.128033,101.639284],"is_wp":0,"line":""},{"name":"Pangsapuri Tiara 2, Jalan 17\/1","id":2801,"code":"1002183","location":[3.125014,101.638434],"is_wp":0,"line":""},{"name":"Shell (1), Jalan 17\/22","id":2802,"code":"1003251","location":[3.124498,101.636892],"is_wp":0,"line":""},{"name":"Happy Garden, Jalan 17\/29","id":2784,"code":"1000899","location":[3.128353,101.635455],"is_wp":0,"line":""},{"name":"Rumah No. 686, Jalan 17\/22","id":2785,"code":"1002957","location":[3.125874,101.635099],"is_wp":0,"line":""},{"name":"Shell, Jalan 17\/22","id":2786,"code":"1003202","location":[3.124796,101.636771],"is_wp":0,"line":""},{"name":"Rumah No. 26, Jalan 17\/1","id":2787,"code":"1002920","location":[3.12072,101.638411],"is_wp":0,"line":""},{"name":"Kolej UIA, Jalan Universiti","id":2803,"code":"1002675","location":[3.118833,101.638656],"is_wp":0,"line":""},{"name":"Masjid UIA, Jalan Universiti","id":2804,"code":"1001955","location":[3.118748,101.641294],"is_wp":0,"line":""},{"name":"SMK Sultan Abdul Samad (opp.), Jalan Universiti","id":2805,"code":"1003407","location":[3.118629,101.64512],"is_wp":0,"line":""},{"name":"Intan, Jalan Universiti","id":2806,"code":"1001007","location":[3.117022,101.649783],"is_wp":0,"line":""},{"name":"Universiti Tower, Jalan Bukit","id":2807,"code":"1004179","location":[3.113483,101.650377],"is_wp":0,"line":""},{"name":"SRK Alam Shah, Jalan Bukit","id":2808,"code":"1003630","location":[3.112234,101.647191],"is_wp":0,"line":""},{"name":"Pangsapuri Ehsan Ria (Opp.), Jalan Bukit","id":2809,"code":"1002142","location":[3.111594,101.64646],"is_wp":0,"line":""},{"name":"Yayasan Salam, Jalan Utara","id":2793,"code":"1004272","location":[3.108535,101.645876],"is_wp":0,"line":""},{"name":"Tasik Taman Jaya, Jalan Timur","id":2810,"code":"1003857","location":[3.104657,101.648219],"is_wp":0,"line":""},{"name":"Dewan Sivik MBPJ, Jalan Yong Shook Lin","id":1938,"code":"1001979","location":[3.098091,101.64554],"is_wp":0,"line":""},{"name":"KK Mart, Jalan Barat","id":2811,"code":"1001509","location":[3.100977,101.641207],"is_wp":0,"line":""},{"name":"Stesen LRT Asia Jaya, Jalan 223","id":2776,"code":"1001784","location":[3.104548,101.63843],"is_wp":0,"line":""}],"trip":{"id":241,"headsign":"Stesen LRT Asia Jaya"}}],"stops":[{"stop":{"name":"Eastin Hotel, Jalan Damansara","id":2608,"code":"1000603","location":[3.128304,101.64286]},"trip":{"id":241,"headsign":"Stesen LRT Asia Jaya"},"route":{"id":81,"code":"T629","type":3,"name":"Stesen LRT Asia Jaya"}},{"stop":{"name":"Stesen LRT Asia Jaya, Jalan 223","id":2776,"code":"1001784","location":[3.104548,101.63843]},"trip":{"id":241,"headsign":"Stesen LRT Asia Jaya"},"route":{"id":81,"code":"T629","type":3,"name":"Stesen LRT Asia Jaya"}}]}]}